mcculw/__init__.py
mcculw/enums.py
mcculw/structs.py
mcculw/ul.py
mcculw/device_info/__init__.py
mcculw/device_info/ai_info.py
mcculw/device_info/ao_info.py
mcculw/device_info/ctr_info.py
mcculw/device_info/daq_device_info.py
mcculw/device_info/daqi_info.py
mcculw/device_info/daqo_info.py
mcculw/device_info/dio_info.py
mcculw-1.0.0.dist-info/LICENSE
mcculw-1.0.0.dist-info/METADATA
mcculw-1.0.0.dist-info/WHEEL
mcculw-1.0.0.dist-info/top_level.txt
mcculw-1.0.0.dist-info/RECORD
