Metadata-Version: 1.1
Name: mcculw
Version: 1.0.0
Summary: MCC Universal Library Python API for Windows
Home-page: http://www.mccdaq.com
Author: Measurement Computing
Author-email: info@mccdaq.com
License: MIT
Keywords: development mcc daq data acquisition
Platform: UNKNOWN
Classifier: Development Status :: 5 - Production/Stable
Classifier: Intended Audience :: Developers
Classifier: Topic :: System :: Hardware :: Hardware Drivers
Classifier: License :: OSI Approved :: MIT License
Classifier: Programming Language :: Python :: 2
Classifier: Programming Language :: Python :: 2.7
Classifier: Programming Language :: Python :: 3
Classifier: Programming Language :: Python :: 3.8
